package-lock.json
package.json
scripts/gen_credits.py
scripts/hatch_build.py
gunicorn.conf.py
main.py
manage.py
firefighter/__init__.py
firefighter/_version.py
firefighter/api/__init__.py
firefighter/api/admin.py
firefighter/api/apps.py
firefighter/api/authentication.py
firefighter/api/models.py
firefighter/api/permissions.py
firefighter/api/renderer.py
firefighter/api/serializers.py
firefighter/api/urls.py
firefighter/api/migrations/0001_initial.py
firefighter/api/migrations/0002_alter_apitokenproxy_options.py
firefighter/api/migrations/0003_alter_apitokenproxy_options.py
firefighter/api/migrations/__init__.py
firefighter/api/views/__init__.py
firefighter/api/views/_base.py
firefighter/api/views/components.py
firefighter/api/views/environments.py
firefighter/api/views/groups.py
firefighter/api/views/incident_cost_types.py
firefighter/api/views/incident_costs.py
firefighter/api/views/incidents.py
firefighter/api/views/severities.py
firefighter/components/__init__.py
firefighter/components/avatar/__init__.py
firefighter/components/avatar/avatar.html
firefighter/components/avatar/avatar.py
firefighter/components/card/__init__.py
firefighter/components/card/card.html
firefighter/components/card/card.py
firefighter/components/export_button/__init__.py
firefighter/components/export_button/export_button.html
firefighter/components/export_button/export_button.py
firefighter/components/form/__init__.py
firefighter/components/form/form.html
firefighter/components/form/form.py
firefighter/components/form_field/__init__.py
firefighter/components/form_field/form_field.html
firefighter/components/form_field/form_field.py
firefighter/components/messages/__init__.py
firefighter/components/messages/messages.html
firefighter/components/messages/messages.py
firefighter/components/modal/__init__.py
firefighter/components/modal/modal.html
firefighter/components/modal/modal.py
firefighter/confluence/__init__.py
firefighter/confluence/admin.py
firefighter/confluence/apps.py
firefighter_incident-0.0.27.dist-info/METADATA
firefighter_incident-0.0.27.dist-info/WHEEL
firefighter_incident-0.0.27.dist-info/entry_points.txt
firefighter_incident-0.0.27.dist-info/licenses/LICENSE
firefighter_incident-0.0.27.dist-info/RECORD
