Metadata-Version: 2.4
Name: firefighter-incident
Version: 0.0.27
Summary: Incident Management tool made for Slack using Django
Project-URL: Repository, https://github.com/ManoManoTech/firefighter-incident
Project-URL: Documentation, https://manomanotech.github.io/firefighter-incident/latest/
Project-URL: Changelog, https://github.com/ManoManoTech/firefighter-incident/releases
Author-email: Gabriel Dugny <gabriel.dugny@manomano.com>, SRE <teamsre@manomano.com>
License: MIT License
License-File: LICENSE
Classifier: Development Status :: 4 - Beta
Classifier: Environment :: Web Environment
Classifier: Framework :: Django
Classifier: Framework :: Django :: 4.2
Classifier: Intended Audience :: Developers
Classifier: Intended Audience :: Information Technology
Classifier: License :: OSI Approved :: MIT License
Classifier: Programming Language :: Python :: 3
Classifier: Programming Language :: Python :: 3 :: Only
Classifier: Programming Language :: Python :: 3.11
Classifier: Programming Language :: Python :: 3.12
Classifier: Typing :: Typed
Requires-Python: <4.0,>=3.11
Requires-Dist: aiohttp>=3.9.1
Requires-Dist: celery[gevent,redis]>=5.3.6
Requires-Dist: dateparser>=1.2.0
Requires-Dist: ddtrace<2.4.0,>=2.3.3
Requires-Dist: django-celery-beat>=2.5.0
Requires-Dist: django-components>=0.101
Requires-Dist: django-filter>=23.4
Requires-Dist: django-htmx>=1.17.2
Requires-Dist: django-import-export>=4.0.0
Requires-Dist: django-oauth2-authcodeflow>=1.0.1
Requires-Dist: django-redis>=5.4.0
Requires-Dist: django-simple-menu>=2.1.3
Requires-Dist: django-stubs-ext~=5.1.1
Requires-Dist: django-tables2>=2.6.0
Requires-Dist: django-taggit>=5.0.1
Requires-Dist: django-widget-tweaks>=1.5.0
Requires-Dist: django[argon2]<5.0.0,>=4.2.8
Requires-Dist: djangorestframework-csv>=3.0.1
Requires-Dist: djangorestframework>=3.14.0
Requires-Dist: docutils>=0.20.1
Requires-Dist: drf-spectacular>=0.26.5
Requires-Dist: drf-standardized-errors>=0.12.6
Requires-Dist: gunicorn>=21.2.0
Requires-Dist: httpx>=0.25.2
Requires-Dist: jira<3.6.0,>=3.5.2
Requires-Dist: markdown>=3.5.1
Requires-Dist: nh3>=0.2.15
Requires-Dist: pdpyras>=5.1.3
Requires-Dist: psycopg[binary]>=3.1.14
Requires-Dist: python-dateutil>=2.8.2
Requires-Dist: python-decouple>=3.8
Requires-Dist: python-json-logger>=2.0.7
Requires-Dist: slack-bolt>=1.18.1
Requires-Dist: slack-sdk>=3.26.1
Requires-Dist: uritemplate>=4.1.1
Requires-Dist: whitenoise>=6.6.0
Requires-Dist: wrapt>=1.17.0
